chem_mat_data/.env
chem_mat_data/ChemMatData_logo_final.png
chem_mat_data/VERSION
chem_mat_data/__init__.py
chem_mat_data/_typing.py
chem_mat_data/cli.py
chem_mat_data/config.py
chem_mat_data/data.py
chem_mat_data/examples/00_quickstart.py
chem_mat_data/graph.py
chem_mat_data/main.py
chem_mat_data/processing.py
chem_mat_data/scripts/assets/_test.csv
chem_mat_data/scripts/create_graph_datasets.py
chem_mat_data/scripts/create_graph_datasets__bace.py
chem_mat_data/scripts/create_graph_datasets__clintox.py
chem_mat_data/scripts/results/create_graph_datasets/debug/analysis.py
chem_mat_data/scripts/results/create_graph_datasets/debug/dataset.mpack
chem_mat_data/scripts/results/create_graph_datasets/debug/experiment_code.py
chem_mat_data/scripts/results/create_graph_datasets/debug/experiment_data.json
chem_mat_data/scripts/results/create_graph_datasets/debug/experiment_meta.json
chem_mat_data/scripts/results/create_graph_datasets/debug/experiment_out.log
chem_mat_data/scripts/results/create_graph_datasets__bace/debug/analysis.py
chem_mat_data/scripts/results/create_graph_datasets__bace/debug/bace.mpack
chem_mat_data/scripts/results/create_graph_datasets__bace/debug/bace.mpack.gz
chem_mat_data/scripts/results/create_graph_datasets__bace/debug/create_graph_datasets.py
chem_mat_data/scripts/results/create_graph_datasets__bace/debug/experiment_code.py
chem_mat_data/scripts/results/create_graph_datasets__bace/debug/experiment_data.json
chem_mat_data/scripts/results/create_graph_datasets__bace/debug/experiment_meta.json
chem_mat_data/scripts/results/create_graph_datasets__bace/debug/experiment_out.log
chem_mat_data/templates/logo.txt
chem_mat_data/testing.py
chem_mat_data/utils.py
chem_mat_data/visualization.py
chem_mat_data/web.py
chem_mat_data-0.1.2.dist-info/LICENSE
chem_mat_data-0.1.2.dist-info/METADATA
chem_mat_data-0.1.2.dist-info/WHEEL
chem_mat_data-0.1.2.dist-info/entry_points.txt
chem_mat_data-0.1.2.dist-info/RECORD
